minimod_opt/__init__.py
minimod_opt/base/__init__.py
minimod_opt/base/basesolver.py
minimod_opt/base/bau_constraint.py
minimod_opt/base/model.py
minimod_opt/continuous/__init__.py
minimod_opt/continuous/costs.py
minimod_opt/continuous/example/example.ipynb
minimod_opt/continuous/exceptions.py
minimod_opt/continuous/optimize.py
minimod_opt/monte_carlo/__init__.py
minimod_opt/monte_carlo/monte_carlo.py
minimod_opt/solvers/__init__.py
minimod_opt/solvers/benefitsolver.py
minimod_opt/solvers/costsolver.py
minimod_opt/tests/__init__.py
minimod_opt/utils/__init__.py
minimod_opt/utils/exceptions.py
minimod_opt/utils/helpers.py
minimod_opt/utils/plotting.py
minimod_opt/utils/summary.py
minimod_opt/utils/suppress_messages.py
minimod_opt-0.1.15.dist-info/LICENSE
minimod_opt-0.1.15.dist-info/WHEEL
minimod_opt-0.1.15.dist-info/METADATA
minimod_opt-0.1.15.dist-info/RECORD
