Metadata-Version: 2.1
Name: minimod-opt
Version: 0.1.15
Summary: A mixed-integer program optimization solver for finding optimal nutritional interventions across space and time.
Home-page: https://minimod-nutrition.github.io/minimod-opt/
License: GPL-3.0-or-later
Keywords: economics,mixed-integer-programming,nutrition
Author: Aleksandr Michuda
Author-email: am2497@cornell.edu
Maintainer: Aleksandr Michuda
Maintainer-email: am2497@cornell.edu
Requires-Python: >=3.8,<4.0
Classifier: License :: OSI Approved :: GNU General Public License v3 or later (GPLv3+)
Classifier: Programming Language :: Python :: 3
Classifier: Programming Language :: Python :: 3.8
Classifier: Programming Language :: Python :: 3.9
Classifier: Programming Language :: Python :: 3.10
Classifier: Programming Language :: Python :: 3.11
Requires-Dist: adjustText (>=0.7.3,<0.8.0)
Requires-Dist: matplotlib (>=3.6.1,<4.0.0)
Requires-Dist: mip (==1.9.3)
Requires-Dist: numpy (>=1.23.4,<2.0.0)
Requires-Dist: pandas (>=1.5.0,<2.0.0)
Requires-Dist: pqdm (>=0.2.0,<0.3.0)
Requires-Dist: progressbar33 (>=2.4,<3.0)
Requires-Dist: python-docx (>=0.8.11,<0.9.0)
Requires-Dist: tabulate (>=0.9.0,<0.10.0)
Requires-Dist: xlrd (>=2.0.1,<3.0.0)
Project-URL: Repository, https://github.com/minimod-nutrition/minimod-opt
